[{"max_depth": 4, "elapsed_time": 1.0794109629314335, "score": 0.9000220458553791, "n_estimators": 200, "min_samples_leaf": 1}, {"max_depth": 4, "elapsed_time": 2.086124645491509, "score": 0.8989197530864198, "n_estimators": 400, "min_samples_leaf": 1}, {"max_depth": 4, "elapsed_time": 3.0058342899083073, "score": 0.8992504409171076, "n_estimators": 600, "min_samples_leaf": 1}, {"max_depth": 4, "elapsed_time": 4.077808596206523, "score": 0.8962742504409171, "n_estimators": 800, "min_samples_leaf": 1}, {"max_depth": 4, "elapsed_time": 5.135452743525093, "score": 0.894510582010582, "n_estimators": 1000, "min_samples_leaf": 1}, {"max_depth": 4, "elapsed_time": 1.0130439137992653, "score": 0.9000220458553791, "n_estimators": 200, "min_samples_leaf": 25}, {"max_depth": 4, "elapsed_time": 2.0456906475646974, "score": 0.8989197530864198, "n_estimators": 400, "min_samples_leaf": 25}, {"max_depth": 4, "elapsed_time": 3.085081033857932, "score": 0.8992504409171076, "n_estimators": 600, "min_samples_leaf": 25}, {"max_depth": 4, "elapsed_time": 4.618433909248779, "score": 0.8962742504409171, "n_estimators": 800, "min_samples_leaf": 25}, {"max_depth": 4, "elapsed_time": 5.393269567102834, "score": 0.8944003527336861, "n_estimators": 1000, "min_samples_leaf": 25}, {"max_depth": 4, "elapsed_time": 1.090914913218512, "score": 0.8996913580246914, "n_estimators": 200, "min_samples_leaf": 50}, {"max_depth": 4, "elapsed_time": 2.2536817895925196, "score": 0.8989197530864198, "n_estimators": 400, "min_samples_leaf": 50}, {"max_depth": 4, "elapsed_time": 5.116605741424792, "score": 0.8984788359788359, "n_estimators": 600, "min_samples_leaf": 50}, {"max_depth": 4, "elapsed_time": 5.241124374531864, "score": 0.8957231040564374, "n_estimators": 800, "min_samples_leaf": 50}, {"max_depth": 4, "elapsed_time": 7.31237201183103, "score": 0.894620811287478, "n_estimators": 1000, "min_samples_leaf": 50}, {"max_depth": 4, "elapsed_time": 1.2379783493688592, "score": 0.8985890652557319, "n_estimators": 200, "min_samples_leaf": 75}, {"max_depth": 4, "elapsed_time": 2.2718271660905884, "score": 0.8974867724867724, "n_estimators": 400, "min_samples_leaf": 75}, {"max_depth": 4, "elapsed_time": 3.0248914923067787, "score": 0.8978174603174603, "n_estimators": 600, "min_samples_leaf": 75}, {"max_depth": 4, "elapsed_time": 4.119907774618696, "score": 0.8951719576719577, "n_estimators": 800, "min_samples_leaf": 75}, {"max_depth": 4, "elapsed_time": 5.140804229624337, "score": 0.8942901234567902, "n_estimators": 1000, "min_samples_leaf": 75}, {"max_depth": 8, "elapsed_time": 2.3415668625802937, "score": 0.9451058201058201, "n_estimators": 200, "min_samples_leaf": 1}, {"max_depth": 8, "elapsed_time": 4.65644937210709, "score": 0.9466490299823633, "n_estimators": 400, "min_samples_leaf": 1}, {"max_depth": 8, "elapsed_time": 6.8973015536757885, "score": 0.9466490299823633, "n_estimators": 600, "min_samples_leaf": 1}, {"max_depth": 8, "elapsed_time": 9.193285742670923, "score": 0.9464285714285714, "n_estimators": 800, "min_samples_leaf": 1}, {"max_depth": 8, "elapsed_time": 11.607090893565328, "score": 0.9468694885361552, "n_estimators": 1000, "min_samples_leaf": 1}, {"max_depth": 8, "elapsed_time": 2.141248031424766, "score": 0.931657848324515, "n_estimators": 200, "min_samples_leaf": 25}, {"max_depth": 8, "elapsed_time": 4.156356177836642, "score": 0.9332010582010583, "n_estimators": 400, "min_samples_leaf": 25}, {"max_depth": 8, "elapsed_time": 6.066865864293504, "score": 0.9343033509700176, "n_estimators": 600, "min_samples_leaf": 25}, {"max_depth": 8, "elapsed_time": 7.980547850947914, "score": 0.9340828924162258, "n_estimators": 800, "min_samples_leaf": 25}, {"max_depth": 8, "elapsed_time": 9.921591183410783, "score": 0.9348544973544973, "n_estimators": 1000, "min_samples_leaf": 25}, {"max_depth": 8, "elapsed_time": 1.7116236659257993, "score": 0.9192019400352733, "n_estimators": 200, "min_samples_leaf": 50}, {"max_depth": 8, "elapsed_time": 3.4146566263189015, "score": 0.9186507936507936, "n_estimators": 400, "min_samples_leaf": 50}, {"max_depth": 8, "elapsed_time": 5.086896064163739, "score": 0.9190917107583775, "n_estimators": 600, "min_samples_leaf": 50}, {"max_depth": 8, "elapsed_time": 6.772485684210551, "score": 0.917989417989418, "n_estimators": 800, "min_samples_leaf": 50}, {"max_depth": 8, "elapsed_time": 9.47117053648617, "score": 0.9185405643738977, "n_estimators": 1000, "min_samples_leaf": 50}, {"max_depth": 8, "elapsed_time": 2.294461468478403, "score": 0.9154541446208113, "n_estimators": 200, "min_samples_leaf": 75}, {"max_depth": 8, "elapsed_time": 3.922312515293015, "score": 0.9128086419753086, "n_estimators": 400, "min_samples_leaf": 75}, {"max_depth": 8, "elapsed_time": 4.950683397297325, "score": 0.912147266313933, "n_estimators": 600, "min_samples_leaf": 75}, {"max_depth": 8, "elapsed_time": 6.2857443143275304, "score": 0.9118165784832452, "n_estimators": 800, "min_samples_leaf": 75}, {"max_depth": 8, "elapsed_time": 7.962781409753006, "score": 0.9111552028218695, "n_estimators": 1000, "min_samples_leaf": 75}, {"max_depth": 16, "elapsed_time": 5.358141895054359, "score": 0.9879850088183422, "n_estimators": 200, "min_samples_leaf": 1}, {"max_depth": 16, "elapsed_time": 10.671811236847134, "score": 0.9871031746031746, "n_estimators": 400, "min_samples_leaf": 1}, {"max_depth": 16, "elapsed_time": 16.80720404044405, "score": 0.9871031746031746, "n_estimators": 600, "min_samples_leaf": 1}, {"max_depth": 16, "elapsed_time": 22.605826407398126, "score": 0.9875440917107584, "n_estimators": 800, "min_samples_leaf": 1}, {"max_depth": 16, "elapsed_time": 26.983497634424566, "score": 0.9880952380952381, "n_estimators": 1000, "min_samples_leaf": 1}, {"max_depth": 16, "elapsed_time": 2.4647807758683484, "score": 0.9379409171075838, "n_estimators": 200, "min_samples_leaf": 25}, {"max_depth": 16, "elapsed_time": 4.900887275163768, "score": 0.9382716049382716, "n_estimators": 400, "min_samples_leaf": 25}, {"max_depth": 16, "elapsed_time": 7.33385308641482, "score": 0.9387125220458554, "n_estimators": 600, "min_samples_leaf": 25}, {"max_depth": 16, "elapsed_time": 10.108573790977971, "score": 0.939484126984127, "n_estimators": 800, "min_samples_leaf": 25}, {"max_depth": 16, "elapsed_time": 12.559206280391663, "score": 0.9397045855379189, "n_estimators": 1000, "min_samples_leaf": 25}, {"max_depth": 16, "elapsed_time": 1.8558177859013085, "score": 0.923941798941799, "n_estimators": 200, "min_samples_leaf": 50}, {"max_depth": 16, "elapsed_time": 3.6230546208753367, "score": 0.9236111111111112, "n_estimators": 400, "min_samples_leaf": 50}, {"max_depth": 16, "elapsed_time": 5.49204400083363, "score": 0.9207451499118166, "n_estimators": 600, "min_samples_leaf": 50}, {"max_depth": 16, "elapsed_time": 7.2899860906509275, "score": 0.9196428571428571, "n_estimators": 800, "min_samples_leaf": 50}, {"max_depth": 16, "elapsed_time": 9.240287678814639, "score": 0.9209656084656085, "n_estimators": 1000, "min_samples_leaf": 50}, {"max_depth": 16, "elapsed_time": 1.5968288493331784, "score": 0.9135802469135802, "n_estimators": 200, "min_samples_leaf": 75}, {"max_depth": 16, "elapsed_time": 3.1682349579514266, "score": 0.9110449735449735, "n_estimators": 400, "min_samples_leaf": 75}, {"max_depth": 16, "elapsed_time": 4.682955547563324, "score": 0.9113756613756614, "n_estimators": 600, "min_samples_leaf": 75}, {"max_depth": 16, "elapsed_time": 6.897949808109843, "score": 0.9118165784832452, "n_estimators": 800, "min_samples_leaf": 75}, {"max_depth": 16, "elapsed_time": 7.930268925005294, "score": 0.9120370370370371, "n_estimators": 1000, "min_samples_leaf": 75}]