[{"max_depth": 8, "min_samples_leaf": 1, "n_estimators": 500, "elapsed_time": 1.3673785186838359, "score": 0.647993943981832}, {"max_depth": 8, "min_samples_leaf": 1, "n_estimators": 1000, "elapsed_time": 2.6934800546150655, "score": 0.6457229371688115}, {"max_depth": 8, "min_samples_leaf": 1, "n_estimators": 1500, "elapsed_time": 3.9460567297646776, "score": 0.6442089326267979}, {"max_depth": 8, "min_samples_leaf": 5, "n_estimators": 500, "elapsed_time": 1.22783091745805, "score": 0.6563209689629069}, {"max_depth": 8, "min_samples_leaf": 5, "n_estimators": 1000, "elapsed_time": 2.479154935805127, "score": 0.6548069644208933}, {"max_depth": 8, "min_samples_leaf": 5, "n_estimators": 1500, "elapsed_time": 3.6922451253049076, "score": 0.651778955336866}, {"max_depth": 16, "min_samples_leaf": 1, "n_estimators": 500, "elapsed_time": 2.2332375636324286, "score": 0.6434519303557911}, {"max_depth": 16, "min_samples_leaf": 1, "n_estimators": 1000, "elapsed_time": 4.43452681787312, "score": 0.6381529144587433}, {"max_depth": 16, "min_samples_leaf": 1, "n_estimators": 1500, "elapsed_time": 6.638254681485705, "score": 0.6373959121877366}, {"max_depth": 16, "min_samples_leaf": 5, "n_estimators": 500, "elapsed_time": 1.5909424702404067, "score": 0.6472369417108251}, {"max_depth": 16, "min_samples_leaf": 5, "n_estimators": 1000, "elapsed_time": 3.1684797991765663, "score": 0.6532929598788796}, {"max_depth": 16, "min_samples_leaf": 5, "n_estimators": 1500, "elapsed_time": 4.752328788046725, "score": 0.6495079485238455}]